INSTALL.txt
README.txt
setup.cfg
setup.py
Products/__init__.py
Products.TALESField.egg-info/PKG-INFO
Products.TALESField.egg-info/SOURCES.txt
Products.TALESField.egg-info/dependency_links.txt
Products.TALESField.egg-info/entry_points.txt
Products.TALESField.egg-info/namespace_packages.txt
Products.TALESField.egg-info/not-zip-safe
Products.TALESField.egg-info/requires.txt
Products.TALESField.egg-info/top_level.txt
Products/TALESField/CHANGES.txt
Products/TALESField/README.txt
Products/TALESField/__init__.py
Products/TALESField/_field.py
Products/TALESField/_tales.py
Products/TALESField/makefile.in
Products/TALESField/validators.py
Products/TALESField/version.txt
Products/TALESField/tests/__init__.py
Products/TALESField/tests/test_field.py