Metadata-Version: 1.0
Name: Products.TALESField
Version: 1.1.3
Summary: An Archetypes field that stores TALES Expressions
Home-page: http://plone.org/products/scriptablefields
Author: Jens Klein
Author-email: jens@bluedynamics.com
License: GPL
Keywords: Plone ScriptableFields TALESField
Platform: UNKNOWN
Classifier: Framework :: Plone
Classifier: Framework :: Zope2
Classifier: Programming Language :: Python
